LICENSE.md
MANIFEST.in
README.rst
setup.cfg
setup.py
versioneer.py
pandas_msgpack/__init__.py
pandas_msgpack/_version.py
pandas_msgpack/move.c
pandas_msgpack/packers.py
pandas_msgpack.egg-info/PKG-INFO
pandas_msgpack.egg-info/SOURCES.txt
pandas_msgpack.egg-info/dependency_links.txt
pandas_msgpack.egg-info/requires.txt
pandas_msgpack.egg-info/top_level.txt
pandas_msgpack/includes/pack.h
pandas_msgpack/includes/pack_template.h
pandas_msgpack/includes/sysdep.h
pandas_msgpack/includes/unpack.h
pandas_msgpack/includes/unpack_define.h
pandas_msgpack/includes/unpack_template.h
pandas_msgpack/msgpack/__init__.py
pandas_msgpack/msgpack/_packer.cpp
pandas_msgpack/msgpack/_packer.pyx
pandas_msgpack/msgpack/_unpacker.cpp
pandas_msgpack/msgpack/_unpacker.pyx
pandas_msgpack/msgpack/_version.py
pandas_msgpack/msgpack/exceptions.py
pandas_msgpack/tests/__init__.py
pandas_msgpack/tests/test_packers.py