Metadata-Version: 1.1
Name: pandas-msgpack
Version: 0.1.4
Summary: Pandas interface to msgpack
Home-page: https://github.com/pydata/pandas-msgpack
Author: The PyData Development Team
Author-email: pydata@googlegroups.com
License: BSD License
Keywords: data
Platform: UNKNOWN
Classifier: Development Status :: 4 - Beta
Classifier: Environment :: Console
Classifier: Intended Audience :: Science/Research
Classifier: Operating System :: OS Independent
Classifier: Programming Language :: Python
Classifier: Programming Language :: Python :: 2
Classifier: Programming Language :: Python :: 2.7
Classifier: Programming Language :: Python :: 3
Classifier: Programming Language :: Python :: 3.4
Classifier: Programming Language :: Python :: 3.5
Classifier: Programming Language :: Python :: 3.6
Classifier: Topic :: Scientific/Engineering
